segmentation_lib/__init__.py
segmentation_lib/example/__init__.py
segmentation_lib/example/example_converter.py
segmentation_lib/example/example_segmentation.py
segmentation_lib/example/recolor.py
segmentation_lib/src/__init__.py
segmentation_lib/src/converter.py
segmentation_lib/src/segmentation.py
segmentation_lib-0.1.3.dist-info/METADATA
segmentation_lib-0.1.3.dist-info/WHEEL
segmentation_lib-0.1.3.dist-info/top_level.txt
segmentation_lib-0.1.3.dist-info/RECORD
